{
    "order": 1,
    "title": "Pembuatan Website Professional",
    "icon": "tabler/desktop",
    "simpleDescription": "Website profesional mulai dari Rp100rb",
    "description": "Layanan pembuatan website untuk berbagai kebutuhan, dengan desain profesional dan fitur lengkap.",
    "thumbnail": "test",
    "startFrom": "100rb",
    "items": [
        {
            "collection": "layanan-item",
            "id": "website-perusahaan"
        },
        {
            "collection": "layanan-item",
            "id": "website-sekolah"
        },
        {
            "collection": "layanan-item",
            "id": "website-berita"
        },
        {
            "collection": "layanan-item",
            "id": "website-sistem-informasi"
        },
        {
            "collection": "layanan-item",
            "id": "website-toko-online"
        },
        {
            "collection": "layanan-item",
            "id": "website-ppdb"
        },
        {
            "collection": "layanan-item",
            "id": "website-lms"
        },
        {
            "collection": "layanan-item",
            "id": "website-custom"
        }
    ],
    "featureDescription": "Dengan layanan kami, dapatkan berbagai keunggulan yang mendukung bisnis Anda.",
    "features": [
        {
            "icon": "tabler/world",
            "name": "Gratis Hosting dan Domain"
        },
        {
            "icon": "tabler/text-square",
            "name": "Desain Responsif dan Berkualitas"
        },
        {
            "icon": "tabler/rocket",
            "name": "Pengerjaan Cepat dan Profesional"
        },
        {
            "icon": "tabler/shield",
            "name": "Garansi Layanan dan Keamanan"
        }
    ]
}
